Metadata-Version: 2.1
Name: iflearner
Version: 0.1.0
Summary: Federated learning package
Home-page: https://github.com/iflytek/iflearner
Author: The iFLYTEK Turing Group
Author-email: 
License: Apache License 2.0
Platform: UNKNOWN
Classifier: Development Status :: 3 - Alpha
Classifier: License :: OSI Approved :: Apache Software License
Classifier: Operating System :: OS Independent
Classifier: Operating System :: MacOS :: MacOS X
Classifier: Operating System :: POSIX :: Linux
Classifier: Programming Language :: Python
Classifier: Programming Language :: Python :: 3
Classifier: Programming Language :: Python :: 3 :: Only
Classifier: Programming Language :: Python :: 3.7
Classifier: Programming Language :: Python :: 3.8
Classifier: Programming Language :: Python :: 3.9
Classifier: Programming Language :: Python :: 3.10
Classifier: Programming Language :: Python :: 3.11
Classifier: Programming Language :: Python :: Implementation :: CPython
Requires-Python: >=3.7
License-File: LICENSE
Requires-Dist: gmpy2 (==2.1.2)
Requires-Dist: grpcio (==1.46.3)
Requires-Dist: grpcio-tools (==1.46.3)
Requires-Dist: loguru (==0.6.0)
Requires-Dist: flask (==2.2.0)
Requires-Dist: matplotlib (==3.3.4)
Requires-Dist: numpy (==1.21.6)
Requires-Dist: protobuf (==3.19.4)
Requires-Dist: pycryptodome (==3.14.1)
Requires-Dist: recommonmark (==0.7.1)
Requires-Dist: urllib3 (==1.26.8)
Requires-Dist: isort (==5.10.1)
Requires-Dist: black (==22.3.0)
Requires-Dist: docformatter (==1.4)
Requires-Dist: mypy (==0.960)
Requires-Dist: flake8 (==4.0.1)
Requires-Dist: mkdocs (==1.3.0)
Requires-Dist: mdx-gh-links (==0.2)
Requires-Dist: markdown (==3.3.7)
Requires-Dist: lightgallery (==0.5)
Requires-Dist: mkdocs-material (==8.3.8)
Requires-Dist: mkdocs-static-i18n (==0.46)
Requires-Dist: mkdocs-awesome-pages-plugin (==2.7.0)
Requires-Dist: mkdocs-render-swagger-plugin (==0.0.3)
Requires-Dist: mkdocs-swagger-ui-tag (==0.3.0)
Requires-Dist: mkdocs-gen-files (==0.3.5)
Requires-Dist: mkdocstrings (==0.19.0)
Requires-Dist: mkdocstrings-python (==0.7.1)
Requires-Dist: setuptools (==62.3.2)
Requires-Dist: twine (==4.0.1)
Requires-Dist: visualdl (==2.3.0)
